odoo/addons/account_payment_return_import_n19/__init__.py
odoo/addons/account_payment_return_import_n19/__manifest__.py
odoo/addons/account_payment_return_import_n19/test_files/test-n19.txt
odoo/addons/account_payment_return_import_n19/tests/__init__.py
odoo/addons/account_payment_return_import_n19/tests/test_import_n19.py
odoo/addons/account_payment_return_import_n19/wizard/__init__.py
odoo/addons/account_payment_return_import_n19/wizard/n19_parser.py
odoo/addons/account_payment_return_import_n19/wizard/payment_return_import.py
odoo_addon_account_payment_return_import_n19-16.0.1.0.0.dist-info/METADATA
odoo_addon_account_payment_return_import_n19-16.0.1.0.0.dist-info/WHEEL
odoo_addon_account_payment_return_import_n19-16.0.1.0.0.dist-info/top_level.txt
odoo_addon_account_payment_return_import_n19-16.0.1.0.0.dist-info/RECORD
