Metadata-Version: 2.2
Name: odoo-addon-account_payment_return_import_n19
Version: 16.0.1.0.0
Summary: This addon allows to import payment returns from Cuaderno/Norma 19 files
Home-page: https://github.com/OCA/l10n-spain/tree/12.0/account_payment_return_import_n19
Author: Odoo Community Association (OCA),Coopdevs SCCL
Author-email: support@odoo-community.org
License: AGPL-3
Classifier: Programming Language :: Python
Classifier: Framework :: Odoo
Classifier: Framework :: Odoo :: 16.0
Classifier: License :: OSI Approved :: GNU Affero General Public License v3
Classifier: Development Status :: 5 - Production/Stable
Requires-Python: >=3.10
Requires-Dist: odoo-addon-account_banking_mandate<16.1dev,>=16.0dev
Requires-Dist: odoo-addon-account_payment_return_import_iso20022<16.1dev,>=16.0dev
Requires-Dist: odoo<16.1dev,>=16.0a
Dynamic: author
Dynamic: author-email
Dynamic: classifier
Dynamic: home-page
Dynamic: license
Dynamic: requires-dist
Dynamic: requires-python
Dynamic: summary
